plantweb/__init__.py
plantweb/__main__.py
plantweb/args.py
plantweb/defaults.py
plantweb/directive.py
plantweb/main.py
plantweb/plantuml.py
plantweb/render.py
plantweb-1.3.0.dist-info/LICENSE
plantweb-1.3.0.dist-info/METADATA
plantweb-1.3.0.dist-info/WHEEL
plantweb-1.3.0.dist-info/entry_points.txt
plantweb-1.3.0.dist-info/top_level.txt
plantweb-1.3.0.dist-info/RECORD
