Metadata-Version: 2.1
Name: plantweb
Version: 1.3.0
Summary: Python client for the PlantUML server
Home-page: https://plantweb.rtfd.io/
Author: Carlos Jenkins
Author-email: carlos@jenkins.co.cr
License: UNKNOWN
Keywords: plantweb
Platform: UNKNOWN
Classifier: Development Status :: 5 - Production/Stable
Classifier: Intended Audience :: Developers
Classifier: License :: OSI Approved :: Apache Software License
Classifier: Natural Language :: English
Classifier: Operating System :: POSIX :: Linux
Classifier: Programming Language :: Python :: 2
Classifier: Programming Language :: Python :: 2.7
Classifier: Programming Language :: Python :: 3
Classifier: Programming Language :: Python :: 3.5
License-File: LICENSE
